claude_explore/__init__.py
claude_explore/cli.py
claude_explore/url_parser.py
claude_explore/workspace.py
claude_explore-0.1.3.dist-info/METADATA
claude_explore-0.1.3.dist-info/WHEEL
claude_explore-0.1.3.dist-info/entry_points.txt
claude_explore-0.1.3.dist-info/licenses/LICENSE
claude_explore-0.1.3.dist-info/RECORD
