Metadata-Version: 2.4
Name: claude-explore
Version: 0.1.3
Summary: Ephemeral workspace manager for exploring GitHub repositories with Claude Code
Project-URL: Homepage, https://github.com/akatz-ai/claude-explore
Project-URL: Repository, https://github.com/akatz-ai/claude-explore
Project-URL: Issues, https://github.com/akatz-ai/claude-explore/issues
Author-email: akatz-ai <katzfeyalex+akatzgh@gmail.com>
License: MIT
License-File: LICENSE
Keywords: claude,claude-code,cli,exploration,github,workspace
Classifier: Development Status :: 3 - Alpha
Classifier: Intended Audience :: Developers
Classifier: License :: OSI Approved :: MIT License
Classifier: Programming Language :: Python :: 3
Classifier: Programming Language :: Python :: 3.10
Classifier: Programming Language :: Python :: 3.11
Classifier: Programming Language :: Python :: 3.12
Requires-Python: >=3.10
Requires-Dist: click>=8.2.1
